FukuML/AdaBoostDecisionTree.py
FukuML/AdaBoostDecisionTree.pyc
FukuML/AdaBoostStump.py
FukuML/AdaBoostStump.pyc
FukuML/Blending.py
FukuML/Blending.pyc
FukuML/DecisionStump.py
FukuML/DecisionStump.pyc
FukuML/DecisionTree.py
FukuML/DecisionTree.pyc
FukuML/GradientBoostDecisionTree.py
FukuML/GradientBoostDecisionTree.pyc
FukuML/KernelLogisticRegression.py
FukuML/KernelLogisticRegression.pyc
FukuML/KernelRidgeRegression.py
FukuML/KernelRidgeRegression.pyc
FukuML/L2RLogisticRegression.py
FukuML/L2RLogisticRegression.pyc
FukuML/LeastSquaresSVM.py
FukuML/LeastSquaresSVM.pyc
FukuML/LinearRegression.py
FukuML/LinearRegression.pyc
FukuML/LogisticRegression.py
FukuML/LogisticRegression.pyc
FukuML/MLBase.py
FukuML/MLBase.pyc
FukuML/NeuralNetwork.py
FukuML/NeuralNetwork.pyc
FukuML/PLA.py
FukuML/PLA.pyc
FukuML/PocketPLA.py
FukuML/PocketPLA.pyc
FukuML/ProbabilisticSVM.py
FukuML/ProbabilisticSVM.pyc
FukuML/RandomForest.py
FukuML/RandomForest.pyc
FukuML/RidgeRegression.py
FukuML/RidgeRegression.pyc
FukuML/SupportVectorMachine.py
FukuML/SupportVectorMachine.pyc
FukuML/SupportVectorRegression.py
FukuML/SupportVectorRegression.pyc
FukuML/Utility.py
FukuML/Utility.pyc
FukuML/__init__.py
FukuML/__init__.pyc
FukuML/dataset/decision_stump_test.dat
FukuML/dataset/decision_stump_train.dat
FukuML/dataset/decision_tree_1_test.dat
FukuML/dataset/decision_tree_1_train.dat
FukuML/dataset/decision_tree_2_test.dat
FukuML/dataset/decision_tree_2_train.dat
FukuML/dataset/digits_binary_test.dat
FukuML/dataset/digits_binary_train.dat
FukuML/dataset/digits_dataset_generate.py
FukuML/dataset/digits_multiclass_test.dat
FukuML/dataset/digits_multiclass_train.dat
FukuML/dataset/emotion.dat
FukuML/dataset/linear_regression_test.dat
FukuML/dataset/linear_regression_train.dat
FukuML/dataset/linear_separable_test.dat
FukuML/dataset/linear_separable_train.dat
FukuML/dataset/logistic_regression_test.dat
FukuML/dataset/logistic_regression_train.dat
FukuML-0.4.1.dist-info/DESCRIPTION.rst
FukuML-0.4.1.dist-info/LICENSE.txt
FukuML-0.4.1.dist-info/METADATA
FukuML-0.4.1.dist-info/RECORD
FukuML-0.4.1.dist-info/WHEEL
FukuML-0.4.1.dist-info/metadata.json
FukuML-0.4.1.dist-info/top_level.txt
