Metadata-Version: 2.0
Name: FukuML
Version: 0.4.1
Summary: Simple machine learning library
Home-page: https://github.com/fukuball/fuku-ml
Author: Fukuball Lin
Author-email: fukuball@gmail.com
License: MIT
Keywords: Machine Learning,Perceptron Learning Algorithm,PLA,Pocket Perceptron Learning Algorithm,Pocket PLA,Linear Regression,Logistic Regression,Ridge Regression,Binay Classifier,Multi Classifier,SVM,Support Vector Machine,Decision Tree,AdaBoost
Platform: UNKNOWN
Classifier: Development Status :: 5 - Production/Stable
Classifier: Intended Audience :: Science/Research
Classifier: Intended Audience :: Developers
Classifier: License :: OSI Approved :: MIT License
Classifier: Operating System :: OS Independent
Classifier: Programming Language :: Python
Classifier: Programming Language :: Python :: 2
Classifier: Programming Language :: Python :: 2.7
Classifier: Programming Language :: Python :: 3
Classifier: Programming Language :: Python :: 3.3
Classifier: Programming Language :: Python :: 3.4
Classifier: Topic :: Education
Classifier: Topic :: Scientific/Engineering
Classifier: Topic :: Scientific/Engineering :: Artificial Intelligence
Classifier: Topic :: Software Development :: Libraries
Classifier: Topic :: Software Development :: Libraries :: Python Modules
Requires-Dist: cvxopt (==1.1.8)
Requires-Dist: numpy (==1.10.4)
Requires-Dist: pep8 (==1.7.0)
Requires-Dist: scikit-learn (==0.17.1)
Requires-Dist: scipy (==0.17.0)
